pandaslookup/__init__.py
pandaslookup/lookup.py
pandaslookup/source.py
pandas_lookup-0.1.4.dist-info/LICENSE
pandas_lookup-0.1.4.dist-info/METADATA
pandas_lookup-0.1.4.dist-info/WHEEL
pandas_lookup-0.1.4.dist-info/top_level.txt
pandas_lookup-0.1.4.dist-info/RECORD
