Metadata-Version: 2.1
Name: pandas-lookup
Version: 0.1.4
Summary: pandas-lookup adds remote lookup tables to a Pandas DataFrame.
Home-page: https://github.com/ghing/pandas-lookup
Author: Geoff Hing
Author-email: geoffhing@gmail.com
License: MIT
Platform: UNKNOWN
Classifier: Development Status :: 4 - Beta
Classifier: Intended Audience :: Developers
Classifier: Intended Audience :: Science/Research
Classifier: License :: OSI Approved :: MIT License
Classifier: Natural Language :: English
Classifier: Operating System :: OS Independent
Classifier: Programming Language :: Python
Classifier: Programming Language :: Python :: 2.7
Classifier: Programming Language :: Python :: 3.6
Classifier: Programming Language :: Python :: 3.7
Classifier: Programming Language :: Python :: Implementation :: CPython
Classifier: Programming Language :: Python :: Implementation :: PyPy
Classifier: Topic :: Multimedia :: Graphics
Classifier: Topic :: Scientific/Engineering :: Information Analysis
Classifier: Topic :: Scientific/Engineering :: Visualization
Classifier: Topic :: Software Development :: Libraries :: Python Modules
Requires-Dist: pandas (>=0.18.1)
Requires-Dist: requests (>=2.9.1)
Requires-Dist: pyyaml (>=3.11)
